yore-0.4.7.dist-info/METADATA
yore-0.4.7.dist-info/WHEEL
yore-0.4.7.dist-info/entry_points.txt
yore-0.4.7.dist-info/licenses/LICENSE
yore/__init__.py
yore/__main__.py
yore/_internal/__init__.py
yore/_internal/cli.py
yore/_internal/config.py
yore/_internal/debug.py
yore/_internal/lib.py
yore/py.typed
yore-0.4.7.dist-info/RECORD
