Metadata-Version: 2.4
Name: yore
Version: 0.4.7
Summary: Manage legacy code with comments.
Author-Email: =?utf-8?q?Timoth=C3=A9e_Mazzucotelli?= <dev@pawamoy.fr>
License-Expression: ISC
License-File: LICENSE
Classifier: Development Status :: 4 - Beta
Classifier: Intended Audience :: Developers
Classifier: Programming Language :: Python
Classifier: Programming Language :: Python :: 3
Classifier: Programming Language :: Python :: 3 :: Only
Classifier: Programming Language :: Python :: 3.10
Classifier: Programming Language :: Python :: 3.11
Classifier: Programming Language :: Python :: 3.12
Classifier: Programming Language :: Python :: 3.13
Classifier: Programming Language :: Python :: 3.14
Classifier: Topic :: Documentation
Classifier: Topic :: Software Development
Classifier: Topic :: Utilities
Classifier: Typing :: Typed
Project-URL: Homepage, https://pawamoy.github.io/yore
Project-URL: Documentation, https://pawamoy.github.io/yore
Project-URL: Changelog, https://pawamoy.github.io/yore/changelog
Project-URL: Repository, https://github.com/pawamoy/yore
Project-URL: Issues, https://github.com/pawamoy/yore/issues
Project-URL: Discussions, https://github.com/pawamoy/yore/discussions
Project-URL: Gitter, https://gitter.im/yore/community
Project-URL: Funding, https://github.com/sponsors/pawamoy
Requires-Python: >=3.10
Requires-Dist: cappa>=0.29
Requires-Dist: humanize>=4.9
Requires-Dist: packaging>=24.1
